wink_sdk_travel_agent/__init__.py
wink_sdk_travel_agent/api_client.py
wink_sdk_travel_agent/api_response.py
wink_sdk_travel_agent/configuration.py
wink_sdk_travel_agent/exceptions.py
wink_sdk_travel_agent/py.typed
wink_sdk_travel_agent/rest.py
wink_sdk_travel_agent/api/__init__.py
wink_sdk_travel_agent/api/analytics_api.py
wink_sdk_travel_agent/api/travel_agent_api.py
wink_sdk_travel_agent/models/__init__.py
wink_sdk_travel_agent/models/address_agent.py
wink_sdk_travel_agent/models/affiliate_account_agent.py
wink_sdk_travel_agent/models/affiliate_account_user_agent.py
wink_sdk_travel_agent/models/agent_booking_request_agent.py
wink_sdk_travel_agent/models/aggregate_descriptor_agent.py
wink_sdk_travel_agent/models/ancillary_request_agent.py
wink_sdk_travel_agent/models/authenticated_user_agent.py
wink_sdk_travel_agent/models/bed_agent.py
wink_sdk_travel_agent/models/bedroom_agent.py
wink_sdk_travel_agent/models/bedroom_configuration_agent.py
wink_sdk_travel_agent/models/beneficiary_agent.py
wink_sdk_travel_agent/models/beneficiary_charge_agent.py
wink_sdk_travel_agent/models/booking_agent.py
wink_sdk_travel_agent/models/booking_analytics_supplier.py
wink_sdk_travel_agent/models/booking_ancillary_agent.py
wink_sdk_travel_agent/models/booking_confirmations_agent.py
wink_sdk_travel_agent/models/booking_contract_agent.py
wink_sdk_travel_agent/models/booking_contract_item_agent.py
wink_sdk_travel_agent/models/booking_contract_payment_details_agent.py
wink_sdk_travel_agent/models/booking_itinerary_agent.py
wink_sdk_travel_agent/models/booking_itinerary_room_configuration_agent.py
wink_sdk_travel_agent/models/booking_itinerary_room_configuration_child_agent.py
wink_sdk_travel_agent/models/booking_overview_request_supplier.py
wink_sdk_travel_agent/models/booking_user_agent.py
wink_sdk_travel_agent/models/booking_user_request_agent.py
wink_sdk_travel_agent/models/booking_user_session_agent.py
wink_sdk_travel_agent/models/booking_view_agent.py
wink_sdk_travel_agent-0.0.57.dist-info/licenses/LICENSE
wink_sdk_travel_agent-0.0.57.dist-info/METADATA
wink_sdk_travel_agent-0.0.57.dist-info/WHEEL
wink_sdk_travel_agent-0.0.57.dist-info/top_level.txt
wink_sdk_travel_agent-0.0.57.dist-info/RECORD
